typespecs/__init__.py
typespecs/api.py
typespecs/py.typed
typespecs/spec.py
typespecs/typing.py
typespecs-1.0.0.dist-info/METADATA
typespecs-1.0.0.dist-info/WHEEL
typespecs-1.0.0.dist-info/licenses/LICENSE
typespecs-1.0.0.dist-info/RECORD
