Metadata-Version: 2.4
Name: typespecs
Version: 1.0.0
Summary: Data specifications by type hints
Project-URL: homepage, https://astropenguin.github.io/typespecs
Project-URL: repository, https://github.com/astropenguin/typespecs
Author-email: Akio Taniguchi <a-taniguchi@mail.kitami-it.ac.jp>
License: MIT License
License-File: LICENSE
Keywords: annotation,dataclass,dataframe,namedtuple,python,specification,typeddict,typing
Classifier: License :: OSI Approved :: MIT License
Classifier: Programming Language :: Python :: 3
Classifier: Programming Language :: Python :: 3.10
Classifier: Programming Language :: Python :: 3.11
Classifier: Programming Language :: Python :: 3.12
Classifier: Programming Language :: Python :: 3.13
Classifier: Programming Language :: Python :: 3.14
Requires-Python: <3.15,>=3.10
Requires-Dist: pandas<3,>=2
Requires-Dist: typing-extensions<5,>=4
